[
  {
    "title": "泰顺无人机表演",
    "description": "5月20日晚，泰顺县文祥湖公园的夜空被1999架无人机点亮，一场以“欢顺520”为主题的无人机灯光秀在此震撼上演。这场由温州交运集团所属低空公司、浙江顺翼泰翔低空经济有限公司联合泰顺县文化和广电旅游体育局共同打造的视觉盛宴，以天为幕、以光为笔，在高空书写了一封跨越半个多世纪的\"时光情书\"，用动态光影演绎\"执子之手，与子偕老\"的深情承诺，为这座浙南山城增添了一抹动人心魄的浪漫注脚。",
    "location": "泰顺县文祥湖公园",
    "date": "2025-05-20",
    "fullDescription": "",
    "coverType": "image",
    "cover": "/uploads/1764296713631-620487281.jpg",
    "media": [
      {
        "type": "video",
        "url": "/uploads/1764296721313-629351170.mp4"
      }
    ],
    "highlights": [],
    "categoryId": 5,
    "service": "航空表演",
    "id": 1764231459722
  },
  {
    "id": 1,
    "categoryId": 1,
    "title": "江心屿无人机外卖配送",
    "description": "江心屿无人机外卖航线，极速送达，空投德克士、永和豆浆等多家外卖",
    "service": "无人机物流服务",
    "location": "江心屿",
    "date": "2025-10-01",
    "views": "1.2k",
    "coverType": "image",
    "cover": "/uploads/1764296738238-439008154.jpg",
    "media": [
      {
        "type": "image",
        "url": "/uploads/1764296744506-267079065.jpg"
      },
      {
        "type": "image",
        "url": "/uploads/1764296748498-687999548.jpg"
      },
      {
        "type": "video",
        "url": "/uploads/1764296752919-602156690.mp4",
        "poster": "https://images.unsplash.com/photo-1473968512647-3e447244af8f?w=800"
      }
    ],
    "fullDescription": "为缓解假期游客密集导致的就餐难等问题，温州交运集团所属低空公司在江心屿创新推出无人机外卖配送服务，以“宋街起飞、九曲桥草坪降落”的双节点布局，在景区内打造“低空物流”内循环。“相比传统地面配送，无人机配送效率提升了近70%，单次能装下2—3份餐食，有效解决配送慢、取餐难等问题。”低空公司一位负责人说，此次在江心屿推出无人机外卖配送服务，进一步探索了“低空物流+景区内循环”的可复制场景，为景区服务增添科技温度。",
    "highlights": [
      "10分钟极速送达，效率提升300%",
      "精准定位空投柜，取餐更方便",
      "覆盖永和豆浆、德克士等种商品",
      "无接触配送，科技感十足"
    ]
  },
  {
    "id": 4,
    "categoryId": 4,
    "title": "山区杨梅无人机吊运",
    "description": "偏远山区农产品无人机空运，解决传统运输方式运输难题",
    "service": "无人机吊运服务",
    "location": "泰顺山区",
    "date": "2025-06-24",
    "views": "1.8k",
    "coverType": "image",
    "cover": "/uploads/1764296782266-332050144.jpg",
    "media": [
      {
        "type": "image",
        "url": "/uploads/1764296786961-152168144.jpg"
      },
      {
        "type": "image",
        "url": "/uploads/1764296790376-159415407.jpg"
      },
      {
        "type": "video",
        "url": "/uploads/1764296794723-372267165.mp4"
      }
    ],
    "fullDescription": "偏远山区，道路崎岖，传统载具运输困难。使用大型吊运无人机，成功杨梅进行吊装配送",
    "highlights": [
      "突破地形限制，吊运能力强",
      "精准定位，误差小于10cm",
      "降低成本40%，缩短工期60%",
      "零安全事故，施工人员零风险"
    ]
  }
]